Raiz/raiz_verilog/control_raiz.v
module control_raiz (

    input clk,
    input start,
    input rst,

    input z,
    input bit_gt_a,
    input a_ge_temp,

    output reg load,
    output reg wr_a,
    output reg shift_res,
    output reg wr_res,
    output reg shift_bit,
    output reg wr_bit,
    output reg wr_temp,
    output reg [1:0] sel_A,
    output reg [1:0] sel_B,
    output reg sel_op,

    output reg done

);

parameter INIT_0         = 4'b0000;
parameter INIT           = 4'b0001;
parameter CHECK_BIT      = 4'b0010;
parameter SHIFT_BIT      = 4'b0011;
parameter ASSIGN_TEMP    = 4'b0100;
parameter CHECK_A        = 4'b0101;
parameter ASSIGN_A       = 4'b0110;
parameter SHIFT_RES_ADD  = 4'b0111;
parameter ASSIGN_RES     = 4'b1000;
parameter SHIFT_RES_ONLY = 4'b1001;
parameter END_STATE      = 4'b1010;

reg [3:0] state;

always @(posedge clk) begin

    if(rst) begin
        state <= INIT_0;
    end

    else begin

        load       <= 0;
        wr_a       <= 0;

        shift_res  <= 0;
        wr_res     <= 0;

        shift_bit  <= 0;
        wr_bit     <= 0;

        wr_temp    <= 0;

        sel_A      <= 2'b00;
        sel_B      <= 2'b00;

        sel_op     <= 0;

        done       <= 0;

        case(state)

            INIT_0: begin

                if(start)
                    state <= INIT;
                else
                    state <= INIT_0;

            end

            INIT: begin

                load <= 1;

                state <= CHECK_BIT;

            end

            CHECK_BIT: begin

                if(bit_gt_a)
                    state <= SHIFT_BIT;

                else if(!z)
                    state <= ASSIGN_TEMP;

                else
                    state <= END_STATE;

            end

            SHIFT_BIT: begin

                shift_bit <= 1;

                state <= CHECK_BIT;

            end

            ASSIGN_TEMP: begin

                wr_temp <= 1;

                sel_A <= 2'b01;
                sel_B <= 2'b01;

                sel_op <= 0;

                state <= CHECK_A;

            end

            CHECK_A: begin

                if(a_ge_temp)
                    state <= ASSIGN_A;

                else
                    state <= SHIFT_RES_ONLY;

            end

            ASSIGN_A: begin

                wr_a <= 1;

                sel_A <= 2'b10;
                sel_B <= 2'b10;

                sel_op <= 1;

                state <= SHIFT_RES_ADD;

            end

            SHIFT_RES_ADD: begin

                shift_res <= 1;

                state <= ASSIGN_RES;

            end

            ASSIGN_RES: begin

                wr_res <= 1;

                sel_A <= 2'b01;
                sel_B <= 2'b01;

                sel_op <= 0;

                state <= SHIFT_BIT;

            end

            SHIFT_RES_ONLY: begin

                shift_res <= 1;

                state <= SHIFT_BIT;

            end

            END_STATE: begin

                done <= 1;

                if(!start)
                    state <= INIT_0;
                else
                    state <= END_STATE;

            end

            default: begin

                state <= INIT_0;

            end

        endcase

    end

end

`ifdef BENCH

reg [8*40:1] state_name;

always @(*) begin

    case(state)

        INIT_0         : state_name = "INIT_0";
        INIT           : state_name = "INIT";
        CHECK_BIT      : state_name = "CHECK_BIT";
        SHIFT_BIT      : state_name = "SHIFT_BIT";
        ASSIGN_TEMP    : state_name = "ASSIGN_TEMP";
        CHECK_A        : state_name = "CHECK_A";
        ASSIGN_A       : state_name = "ASSIGN_A";
        SHIFT_RES_ADD  : state_name = "SHIFT_RES_ADD";
        ASSIGN_RES     : state_name = "ASSIGN_RES";
        SHIFT_RES_ONLY : state_name = "SHIFT_RES_ONLY";
        END_STATE      : state_name = "END_STATE";

        default:
            state_name = "UNKNOWN";

    endcase

end

`endif

endmodule

Raiz/raiz_verilog/comp.v
module comp (

    input [31:0] A,
    input [31:0] bit1,
    input [31:0] temp,

    output z,
    output bit_gt_a,
    output a_ge_temp

);

assign z = (bit1 == 0);
assign bit_gt_a   = (bit1 > A);
assign a_ge_temp  = (A >= temp);

endmodule

Raiz/raiz_verilog/alu.v
module alu (
    input [31:0] A,
    input [31:0] B,
    input alu_op,

    output reg [31:0] result
);

always @(*) begin

    case(alu_op)

        0:
            result = A + B;

        1:
            result = A - B;

    endcase

end
    
endmodule

Raiz/raiz_verilog/mux.v
module mux(

    input [31:0] A,
    input [31:0] B,
    input [31:0] C,

    input [1:0] sel,

    output reg [31:0] Y

);

always @(*) begin

    case(sel)

        2'b00:
            Y = A;

        2'b01:
            Y = B;

        2'b10:
            Y = C;

        default:
            Y = 32'd0;

    endcase

end

endmodule

Raiz/raiz_verilog/reg_Basic.v
module reg_Basic(
    input clk,
    input [31:0] in,
    input [31:0] alu_out,
    input load,
    input wr,

    output reg [31:0] out
);

always @(negedge clk) begin

    if(load)
        out <= in;

    else if(wr)
        out <= alu_out;

end

endmodule

Raiz/raiz_verilog/reg_Shift2.v
module reg_Shift2(
    input clk,

    input [31:0] alu_out,

    input shift,
    input load,
    input wr,

    output reg [31:0] bit1
);

always @(negedge clk) begin

    if(load)
        bit1 <= 32'h40000000;

    else if(wr)
        bit1 <= alu_out;

    else if(shift)
        bit1 <= bit1 >> 2;

end

endmodule

Raiz/raiz_verilog/reg_Shift1.v
module reg_Shift1(
    input clk,

    input [31:0] alu_out,

    input shift,
    input load,
    input wr,

    output reg [31:0] res
);

always @(negedge clk) begin

    if(load)
        res <= 0;

    else if(wr)
        res <= alu_out;

    else if(shift)
        res <= res >> 1;

end

endmodule

Raiz/raiz_verilog/raiz32.v
module raiz32 (
    input clk,
    input rst,
    input start,

    input [31:0] A,

    output [31:0] Result,
    output done

);

    wire load, wr_a, shift_res, wr_res, shift_bit, wr_bit, wr_temp, sel_op;
    wire [1:0] sel_A;
    wire [1:0] sel_B;
    wire z, bit_gt_a, a_ge_temp;
    wire [31:0] alu_out;

    wire [31:0] reg_A_out ;
    wire [31:0] reg_res_out ;
    wire [31:0] reg_bit_out ;
    wire [31:0] reg_temp_out ;

    wire [31:0] aluA_in ;
    wire [31:0] aluB_in ;


    reg_Basic reg_A(
        .clk(clk),
        .in(A),
        .alu_out(alu_out),
        .load(load),
        .wr(wr_a),
        .out(reg_A_out)
    );
    reg_Shift1 reg_res(
        .clk(clk),
        .alu_out(alu_out),
        .shift(shift_res),
        .load(load),
        .wr(wr_res),
        .res(reg_res_out)
    );
    reg_Shift2 reg_bit(
        .clk(clk),
        .alu_out(alu_out),
        .shift(shift_bit),
        .load(load),
        .wr(wr_bit),
        .bit1(reg_bit_out)
    );
    reg_Basic reg_temp(
        .clk(clk),
        .in(32'b0),
        .alu_out(alu_out),
        .load(load),
        .wr(wr_temp),
        .out(reg_temp_out)
    );

    mux muxA(
        .A(reg_bit_out),
        .B(reg_res_out),
        .C(reg_A_out),
        .sel(sel_A),
        .Y(aluA_in)
    );
    mux muxB(
        .A(reg_res_out),
        .B(reg_bit_out),
        .C(reg_temp_out),
        .sel(sel_B),
        .Y(aluB_in)
    );
    alu alu1(
        .A(aluA_in),
        .B(aluB_in),
        .alu_op(sel_op),
        .result(alu_out)
    );
    comp comp1(
        .A(reg_A_out),
        .bit1(reg_bit_out),
        .temp(reg_temp_out),
        .z(z),
        .bit_gt_a(bit_gt_a),
        .a_ge_temp(a_ge_temp)
    );
    control_raiz ctrl(
        .clk(clk),
        .start(start),
        .rst(rst),
        .z(z),
        .bit_gt_a(bit_gt_a),
        .a_ge_temp(a_ge_temp),
        .load(load),
        .wr_a(wr_a),
        .shift_res(shift_res),
        .wr_res(wr_res),
        .shift_bit(shift_bit),
        .wr_bit(wr_bit),
        .wr_temp(wr_temp),
        .sel_A(sel_A),
        .sel_B(sel_B),
        .sel_op(sel_op),
        .done(done)
    );
    assign Result = reg_res_out[15:0];
endmodule

Raiz/raiz_verilog/raiz32_TB.v
`timescale 1ns / 1ps

module raiz32_TB;

reg clk;
reg rst;
reg start;

reg [31:0] A;

wire [15:0] Result;
wire done;

raiz32 DUT(
    .clk(clk),
    .rst(rst),
    .start(start),
    .A(A),
    .Result(Result),
    .done(done)
);

parameter PERIOD = 20;

initial
    clk = 0;

always #(PERIOD/2)
    clk = ~clk;

task run_test;

    input [31:0] value;
    input [15:0] expected;

begin

    @(negedge clk);

    A = value;
    start = 1;

    @(negedge clk);

    start = 0;

    wait(done);

    @(negedge clk);

    if(Result == expected)
        $display("PASS | A = %d | Result = %d", value, Result);
    else
        $display("FAIL | A = %d | Result = %d | Expected = %d",
                 value, Result, expected);

    @(negedge clk);

end

endtask

initial begin

    rst = 0;
    start = 0;
    A = 0;

    @(negedge clk);
    rst = 1;

    @(negedge clk);
    rst = 0;

    //run_test(0, 0);
    //run_test(1, 1);
    run_test(4, 2);
    //run_test(9, 3);
    //run_test(16, 4);
    //run_test(25, 5);
    //run_test(121, 11);
    //run_test(1024, 32);
    //run_test(65535, 255);

    #100;

    $finish;

end

initial begin

    $dumpfile("raiz32_TB.vcd");
    $dumpvars(0, raiz32_TB);

end

endmodule

Raiz/raiz_verilog/raiz32_TB.vcd
$date
	Sun May 24 12:49:18 2026
$end
$version
	Icarus Verilog
$end
$timescale
	1ps
$end
$scope module raiz32_TB $end
$var wire 1 ! done $end
$var wire 16 " Result [15:0] $end
$var parameter 32 # PERIOD $end
$var reg 32 $ A [31:0] $end
$var reg 1 % clk $end
$var reg 1 & rst $end
$var reg 1 ' start $end
$scope module DUT $end
$var wire 32 ( A [31:0] $end
$var wire 1 % clk $end
$var wire 1 & rst $end
$var wire 1 ' start $end
$var wire 1 ) z $end
$var wire 1 * wr_temp $end
$var wire 1 + wr_res $end
$var wire 1 , wr_bit $end
$var wire 1 - wr_a $end
$var wire 1 . shift_res $end
$var wire 1 / shift_bit $end
$var wire 1 0 sel_op $end
$var wire 2 1 sel_B [1:0] $end
$var wire 2 2 sel_A [1:0] $end
$var wire 32 3 reg_temp_out [31:0] $end
$var wire 32 4 reg_res_out [31:0] $end
$var wire 32 5 reg_bit_out [31:0] $end
$var wire 32 6 reg_A_out [31:0] $end
$var wire 1 7 load $end
$var wire 1 ! done $end
$var wire 1 8 bit_gt_a $end
$var wire 32 9 alu_out [31:0] $end
$var wire 32 : aluB_in [31:0] $end
$var wire 32 ; aluA_in [31:0] $end
$var wire 1 < a_ge_temp $end
$var wire 32 = Result [31:0] $end
$scope module alu1 $end
$var wire 1 0 alu_op $end
$var wire 32 > B [31:0] $end
$var wire 32 ? A [31:0] $end
$var reg 32 @ result [31:0] $end
$upscope $end
$scope module comp1 $end
$var wire 1 ) z $end
$var wire 32 A temp [31:0] $end
$var wire 1 8 bit_gt_a $end
$var wire 32 B bit1 [31:0] $end
$var wire 1 < a_ge_temp $end
$var wire 32 C A [31:0] $end
$upscope $end
$scope module ctrl $end
$var wire 1 < a_ge_temp $end
$var wire 1 8 bit_gt_a $end
$var wire 1 % clk $end
$var wire 1 & rst $end
$var wire 1 ' start $end
$var wire 1 ) z $end
$var parameter 4 D ASSIGN_A $end
$var parameter 4 E ASSIGN_RES $end
$var parameter 4 F ASSIGN_TEMP $end
$var parameter 4 G CHECK_A $end
$var parameter 4 H CHECK_BIT $end
$var parameter 4 I END_STATE $end
$var parameter 4 J INIT $end
$var parameter 4 K INIT_0 $end
$var parameter 4 L SHIFT_BIT $end
$var parameter 4 M SHIFT_RES_ADD $end
$var parameter 4 N SHIFT_RES_ONLY $end
$var reg 1 ! done $end
$var reg 1 7 load $end
$var reg 2 O sel_A [1:0] $end
$var reg 2 P sel_B [1:0] $end
$var reg 1 0 sel_op $end
$var reg 1 / shift_bit $end
$var reg 1 . shift_res $end
$var reg 4 Q state [3:0] $end
$var reg 320 R state_name [320:1] $end
$var reg 1 - wr_a $end
$var reg 1 , wr_bit $end
$var reg 1 + wr_res $end
$var reg 1 * wr_temp $end
$upscope $end
$scope module muxA $end
$var wire 2 S sel [1:0] $end
$var wire 32 T C [31:0] $end
$var wire 32 U B [31:0] $end
$var wire 32 V A [31:0] $end
$var reg 32 W Y [31:0] $end
$upscope $end
$scope module muxB $end
$var wire 2 X sel [1:0] $end
$var wire 32 Y C [31:0] $end
$var wire 32 Z B [31:0] $end
$var wire 32 [ A [31:0] $end
$var reg 32 \ Y [31:0] $end
$upscope $end
$scope module reg_A $end
$var wire 32 ] alu_out [31:0] $end
$var wire 1 % clk $end
$var wire 32 ^ in [31:0] $end
$var wire 1 7 load $end
$var wire 1 - wr $end
$var reg 32 _ out [31:0] $end
$upscope $end
$scope module reg_bit $end
$var wire 32 ` alu_out [31:0] $end
$var wire 1 % clk $end
$var wire 1 7 load $end
$var wire 1 / shift $end
$var wire 1 , wr $end
$var reg 32 a bit1 [31:0] $end
$upscope $end
$scope module reg_res $end
$var wire 32 b alu_out [31:0] $end
$var wire 1 % clk $end
$var wire 1 7 load $end
$var wire 1 . shift $end
$var wire 1 + wr $end
$var reg 32 c res [31:0] $end
$upscope $end
$scope module reg_temp $end
$var wire 32 d alu_out [31:0] $end
$var wire 1 % clk $end
$var wire 32 e in [31:0] $end
$var wire 1 7 load $end
$var wire 1 * wr $end
$var reg 32 f out [31:0] $end
$upscope $end
$upscope $end
$scope task run_test $end
$var reg 16 g expected [15:0] $end
$var reg 32 h value [31:0] $end
$upscope $end
$upscope $end
$enddefinitions $end
$comment Show the parameter values. $end
$dumpall
b1001 N
b111 M
b11 L
b0 K
b1 J
b1010 I
b10 H
b101 G
b100 F
b1000 E
b110 D
b10100 #
$end
#0
$dumpvars
bx h
bx g
bx f
b0 e
bx d
bx c
bx b
bx a
bx `
bx _
b0 ^
bx ]
bx \
bx [
bx Z
bx Y
bx X
bx W
bx V
bx U
bx T
bx S
bx R
bx Q
bx P
bx O
bx C
bx B
bx A
bx @
bx ?
bx >
b0xxxxxxxxxxxxxxxx =
x<
bx ;
bx :
bx 9
x8
x7
bx 6
bx 5
bx 4
bx 3
bx 2
bx 1
x0
x/
x.
x-
x,
x+
x*
x)
b0 (
0'
0&
0%
b0 $
bx "
x!
$end
#10000
b10010010100111001001001010101000101111100110000 R
b0 Q
0!
00
b0 1
b0 P
b0 X
b0 2
b0 O
b0 S
0*
0,
0/
0+
0.
0-
07
1%
#20000
1&
0%
#30000
1%
#40000
b10 g
b100 h
0&
0%
#50000
1%
#60000
1'
b100 $
b100 (
b100 ^
0%
#70000
b1001001010011100100100101010100 R
b1 Q
1%
#80000
0'
0%
#90000
b10000110100100001000101010000110100101101011111010000100100100101010100 R
b10 Q
17
1%
#100000
b0 "
b1000000000000000000000000000000 9
b1000000000000000000000000000000 @
b1000000000000000000000000000000 ]
b1000000000000000000000000000000 `
b1000000000000000000000000000000 b
b1000000000000000000000000000000 d
b0 =
b0 :
b0 >
b0 \
b1000000000000000000000000000000 ;
b1000000000000000000000000000000 ?
b1000000000000000000000000000000 W
1<
b0 3
b0 A
b0 Y
b0 f
18
0)
b1000000000000000000000000000000 5
b1000000000000000000000000000000 B
b1000000000000000000000000000000 V
b1000000000000000000000000000000 Z
b1000000000000000000000000000000 a
b0 4
b0 U
b0 [
b0 c
b100 6
b100 C
b100 T
b100 _
0%
#110000
b10100110100100001001001010001100101010001011111010000100100100101010100 R
b11 Q
07
1%
#120000
0%
#130000
b10000110100100001000101010000110100101101011111010000100100100101010100 R
b10 Q
1/
1%
#140000
b10000000000000000000000000000 9
b10000000000000000000000000000 @
b10000000000000000000000000000 ]
b10000000000000000000000000000 `
b10000000000000000000000000000 b
b10000000000000000000000000000 d
b10000000000000000000000000000 ;
b10000000000000000000000000000 ?
b10000000000000000000000000000 W
b10000000000000000000000000000 5
b10000000000000000000000000000 B
b10000000000000000000000000000 V
b10000000000000000000000000000 Z
b10000000000000000000000000000 a
0%
#150000
b10100110100100001001001010001100101010001011111010000100100100101010100 R
b11 Q
0/
1%
#160000
0%
#170000
b10000110100100001000101010000110100101101011111010000100100100101010100 R
b10 Q
1/
1%
#180000
b100000000000000000000000000 9
b100000000000000000000000000 @
b100000000000000000000000000 ]
b100000000000000000000000000 `
b100000000000000000000000000 b
b100000000000000000000000000 d
b100000000000000000000000000 ;
b100000000000000000000000000 ?
b100000000000000000000000000 W
b100000000000000000000000000 5
b100000000000000000000000000 B
b100000000000000000000000000 V
b100000000000000000000000000 Z
b100000000000000000000000000 a
0%
#190000
b10100110100100001001001010001100101010001011111010000100100100101010100 R
b11 Q
0/
1%
#200000
0%
#210000
b10000110100100001000101010000110100101101011111010000100100100101010100 R
b10 Q
1/
1%
#220000
b1000000000000000000000000 9
b1000000000000000000000000 @
b1000000000000000000000000 ]
b1000000000000000000000000 `
b1000000000000000000000000 b
b1000000000000000000000000 d
b1000000000000000000000000 ;
b1000000000000000000000000 ?
b1000000000000000000000000 W
b1000000000000000000000000 5
b1000000000000000000000000 B
b1000000000000000000000000 V
b1000000000000000000000000 Z
b1000000000000000000000000 a
0%
#230000
b10100110100100001001001010001100101010001011111010000100100100101010100 R
b11 Q
0/
1%
#240000
0%
#250000
b10000110100100001000101010000110100101101011111010000100100100101010100 R
b10 Q
1/
1%
#260000
b10000000000000000000000 9
b10000000000000000000000 @
b10000000000000000000000 ]
b10000000000000000000000 `
b10000000000000000000000 b
b10000000000000000000000 d
b10000000000000000000000 ;
b10000000000000000000000 ?
b10000000000000000000000 W
b10000000000000000000000 5
b10000000000000000000000 B
b10000000000000000000000 V
b10000000000000000000000 Z
b10000000000000000000000 a
0%
#270000
b10100110100100001001001010001100101010001011111010000100100100101010100 R
b11 Q
0/
1%
#280000
0%
#290000
b10000110100100001000101010000110100101101011111010000100100100101010100 R
b10 Q
1/
1%
#300000
b100000000000000000000 9
b100000000000000000000 @
b100000000000000000000 ]
b100000000000000000000 `
b100000000000000000000 b
b100000000000000000000 d
b100000000000000000000 ;
b100000000000000000000 ?
b100000000000000000000 W
b100000000000000000000 5
b100000000000000000000 B
b100000000000000000000 V
b100000000000000000000 Z
b100000000000000000000 a
0%
#310000
b10100110100100001001001010001100101010001011111010000100100100101010100 R
b11 Q
0/
1%
#320000
0%
#330000
b10000110100100001000101010000110100101101011111010000100100100101010100 R
b10 Q
1/
1%
#340000
b1000000000000000000 9
b1000000000000000000 @
b1000000000000000000 ]
b1000000000000000000 `
b1000000000000000000 b
b1000000000000000000 d
b1000000000000000000 ;
b1000000000000000000 ?
b1000000000000000000 W
b1000000000000000000 5
b1000000000000000000 B
b1000000000000000000 V
b1000000000000000000 Z
b1000000000000000000 a
0%
#350000
b10100110100100001001001010001100101010001011111010000100100100101010100 R
b11 Q
0/
1%
#360000
0%
#370000
b10000110100100001000101010000110100101101011111010000100100100101010100 R
b10 Q
1/
1%
#380000
b10000000000000000 9
b10000000000000000 @
b10000000000000000 ]
b10000000000000000 `
b10000000000000000 b
b10000000000000000 d
b10000000000000000 ;
b10000000000000000 ?
b10000000000000000 W
b10000000000000000 5
b10000000000000000 B
b10000000000000000 V
b10000000000000000 Z
b10000000000000000 a
0%
#390000
b10100110100100001001001010001100101010001011111010000100100100101010100 R
b11 Q
0/
1%
#400000
0%
#410000
b10000110100100001000101010000110100101101011111010000100100100101010100 R
b10 Q
1/
1%
#420000
b100000000000000 9
b100000000000000 @
b100000000000000 ]
b100000000000000 `
b100000000000000 b
b100000000000000 d
b100000000000000 ;
b100000000000000 ?
b100000000000000 W
b100000000000000 5
b100000000000000 B
b100000000000000 V
b100000000000000 Z
b100000000000000 a
0%
#430000
b10100110100100001001001010001100101010001011111010000100100100101010100 R
b11 Q
0/
1%
#440000
0%
#450000
b10000110100100001000101010000110100101101011111010000100100100101010100 R
b10 Q
1/
1%
#460000
b1000000000000 9
b1000000000000 @
b1000000000000 ]
b1000000000000 `
b1000000000000 b
b1000000000000 d
b1000000000000 ;
b1000000000000 ?
b1000000000000 W
b1000000000000 5
b1000000000000 B
b1000000000000 V
b1000000000000 Z
b1000000000000 a
0%
#470000
b10100110100100001001001010001100101010001011111010000100100100101010100 R
b11 Q
0/
1%
#480000
0%
#490000
b10000110100100001000101010000110100101101011111010000100100100101010100 R
b10 Q
1/
1%
#500000
b10000000000 9
b10000000000 @
b10000000000 ]
b10000000000 `
b10000000000 b
b10000000000 d
b10000000000 ;
b10000000000 ?
b10000000000 W
b10000000000 5
b10000000000 B
b10000000000 V
b10000000000 Z
b10000000000 a
0%
#510000
b10100110100100001001001010001100101010001011111010000100100100101010100 R
b11 Q
0/
1%
#520000
0%
#530000
b10000110100100001000101010000110100101101011111010000100100100101010100 R
b10 Q
1/
1%
#540000
b100000000 9
b100000000 @
b100000000 ]
b100000000 `
b100000000 b
b100000000 d
b100000000 ;
b100000000 ?
b100000000 W
b100000000 5
b100000000 B
b100000000 V
b100000000 Z
b100000000 a
0%
#550000
b10100110100100001001001010001100101010001011111010000100100100101010100 R
b11 Q
0/
1%
#560000
0%
#570000
b10000110100100001000101010000110100101101011111010000100100100101010100 R
b10 Q
1/
1%
#580000
b1000000 9
b1000000 @
b1000000 ]
b1000000 `
b1000000 b
b1000000 d
b1000000 ;
b1000000 ?
b1000000 W
b1000000 5
b1000000 B
b1000000 V
b1000000 Z
b1000000 a
0%
#590000
b10100110100100001001001010001100101010001011111010000100100100101010100 R
b11 Q
0/
1%
#600000
0%
#610000
b10000110100100001000101010000110100101101011111010000100100100101010100 R
b10 Q
1/
1%
#620000
b10000 9
b10000 @
b10000 ]
b10000 `
b10000 b
b10000 d
b10000 ;
b10000 ?
b10000 W
b10000 5
b10000 B
b10000 V
b10000 Z
b10000 a
0%
#630000
b10100110100100001001001010001100101010001011111010000100100100101010100 R
b11 Q
0/
1%
#640000
0%
#650000
b10000110100100001000101010000110100101101011111010000100100100101010100 R
b10 Q
1/
1%
#660000
b100 9
b100 @
b100 ]
b100 `
b100 b
b100 d
b100 ;
b100 ?
b100 W
08
b100 5
b100 B
b100 V
b100 Z
b100 a
0%
#670000
b100000101010011010100110100100101000111010011100101111101010100010001010100110101010000 R
b100 Q
0/
1%
#680000
0%
#690000
b1000011010010000100010101000011010010110101111101000001 R
b100 :
b100 >
b100 \
b0 ;
b0 ?
b0 W
b101 Q
b1 1
b1 P
b1 X
b1 2
b1 O
b1 S
1*
1%
#700000
b100 3
b100 A
b100 Y
b100 f
0%
#710000
b100000101010011010100110100100101000111010011100101111101000001 R
b0 :
b0 >
b0 \
b100 ;
b100 ?
b100 W
b110 Q
b0 1
b0 P
b0 X
b0 2
b0 O
b0 S
0*
1%
#720000
0%
#730000
b1010011010010000100100101000110010101000101111101010010010001010101001101011111010000010100010001000100 R
b0 9
b0 @
b0 ]
b0 `
b0 b
b0 d
b100 :
b100 >
b100 \
b111 Q
10
b10 1
b10 P
b10 X
b10 2
b10 O
b10 S
1-
1%
#740000
b11111111111111111111111111111100 9
b11111111111111111111111111111100 @
b11111111111111111111111111111100 ]
b11111111111111111111111111111100 `
b11111111111111111111111111111100 b
b11111111111111111111111111111100 d
b0 ;
b0 ?
b0 W
0<
18
b0 6
b0 C
b0 T
b0 _
0%
#750000
b1000001010100110101001101001001010001110100111001011111010100100100010101010011 R
b100 9
b100 @
b100 ]
b100 `
b100 b
b100 d
b0 :
b0 >
b0 \
b100 ;
b100 ?
b100 W
b1000 Q
1.
00
b0 1
b0 P
b0 X
b0 2
b0 O
b0 S
0-
1%
#760000
0%
#770000
b10100110100100001001001010001100101010001011111010000100100100101010100 R
b100 :
b100 >
b100 \
b0 ;
b0 ?
b0 W
b11 Q
b1 1
b1 P
b1 X
b1 2
b1 O
b1 S
1+
0.
1%
#780000
b100 "
b1000 9
b1000 @
b1000 ]
b1000 `
b1000 b
b1000 d
b100 =
b100 ;
b100 ?
b100 W
b100 4
b100 U
b100 [
b100 c
0%
#790000
b10000110100100001000101010000110100101101011111010000100100100101010100 R
b10 Q
1/
b0 1
b0 P
b0 X
b0 2
b0 O
b0 S
0+
1%
#800000
b101 9
b101 @
b101 ]
b101 `
b101 b
b101 d
b1 ;
b1 ?
b1 W
b1 5
b1 B
b1 V
b1 Z
b1 a
0%
#810000
b10100110100100001001001010001100101010001011111010000100100100101010100 R
b11 Q
0/
1%
#820000
0%
#830000
b10000110100100001000101010000110100101101011111010000100100100101010100 R
b10 Q
1/
1%
#840000
b100 9
b100 @
b100 ]
b100 `
b100 b
b100 d
b0 ;
b0 ?
b0 W
08
1)
b0 5
b0 B
b0 V
b0 Z
b0 a
0%
#850000
b10001010100111001000100010111110101001101010100010000010101010001000101 R
b1010 Q
0/
1%
#860000
0%
#870000
b10010010100111001001001010101000101111100110000 R
b0 Q
1!
1%
#880000
0%
#890000
0!
1%
