Raiz/raiz_verilog/control_raiz.v
module control_raiz (

    input clk,
    input start,
    input rst,

    input z,
    input bit_gt_a,
    input a_ge_temp,

    output reg load,
    output reg wr_a,
    output reg shift_res,
    output reg wr_res,
    output reg shift_bit,
    output reg wr_bit,
    output reg wr_temp,
    output reg [1:0] sel_A,
    output reg [1:0] sel_B,
    output reg sel_op,

    output reg done

);

parameter INIT_0         = 4'b0000;
parameter INIT           = 4'b0001;
parameter CHECK_BIT      = 4'b0010;
parameter SHIFT_BIT      = 4'b0011;
parameter ASSIGN_TEMP    = 4'b0100;
parameter CHECK_A        = 4'b0101;
parameter ASSIGN_A       = 4'b0110;
parameter ASSIGN_RES     = 4'b0111;
parameter SHIFT_RES_ONLY = 4'b1000;
parameter END_STATE      = 4'b1001;
parameter SHIFT_RES_ADD  = 4'b1010;

reg [3:0] state;
always @(posedge clk) begin

    if(rst) begin
        state <= INIT_0;
    end

    else begin

        case(state)

            INIT_0: begin
                if(start)
                    state <= INIT;
                else
                    state <= INIT_0;

            end

            INIT: begin
                state <= CHECK_BIT;

            end

            CHECK_BIT: begin

                if(bit_gt_a)
                    state <= SHIFT_BIT;

                else if(!z)
                    state <= ASSIGN_TEMP;

                else
                    state <= END_STATE;

            end

            SHIFT_BIT: begin
                // Evaluamos la condición de salida justo DESPUÉS de desplazar el bit de control
                if (z)
                    state <= END_STATE;
                else
                    state <= CHECK_BIT;
            end

            ASSIGN_TEMP: begin
                state <= CHECK_A;

            end

            CHECK_A: begin

                if(a_ge_temp)
                    state <= ASSIGN_A;

                else
                    state <= SHIFT_RES_ONLY;

            end

            ASSIGN_A: begin
                state <= SHIFT_RES_ADD;
                // state <= ASSIGN_RES;

            end

            SHIFT_RES_ADD: begin
                state <= ASSIGN_RES;
            end

            ASSIGN_RES: begin
                state <= SHIFT_BIT;
            end

            SHIFT_RES_ONLY: begin
                state <= SHIFT_BIT;
            end

            END_STATE: begin
                state<= INIT_0;
            end

            default: state <= INIT_0;

        endcase

    end

end

always @(*) begin
    load       = 0;
    wr_a       = 0;
    shift_res  = 0;
    wr_res     = 0;
    shift_bit  = 0;
    wr_bit     = 0;
    wr_temp    = 0;
    sel_A      = 2'b00;
    sel_B      = 2'b00;
    sel_op     = 0;
    done       = 0;
    case (state)
        INIT: begin
            load = 1;
        end
        SHIFT_BIT: begin
            shift_bit = 1;
        end
        ASSIGN_TEMP: begin
            wr_temp = 1;
            sel_A = 2'b01;
            sel_B = 2'b01;
            sel_op = 0;
        end
        ASSIGN_A: begin
            wr_a = 1;
            sel_A = 2'b10;
            sel_B = 2'b10;
            sel_op = 1;
        end

        SHIFT_RES_ADD: begin
            shift_res = 1;
        end

        ASSIGN_RES: begin
            wr_res = 1;
            // sel_A = 2'b11;
            // sel_B = 2'b10;
            sel_A = 2'b01;
            sel_B = 2'b01;
            sel_op = 0;
        end

        SHIFT_RES_ONLY: begin
            shift_res = 1;
        end
        END_STATE: begin
            done = 1;
        end
        default: begin
            load      = 0;
            wr_a      = 0;
            shift_res = 0;
            wr_res    = 0;
            shift_bit = 0;
            wr_bit    = 0;
            wr_temp   = 0;
            sel_A     = 2'b00;
            sel_B     = 2'b00;
            sel_op    = 0;
            done      = 0;
        end
    endcase
end

`ifdef BENCH

reg [8*40:1] state_name;

always @(*) begin

    case(state)
        INIT_0         : state_name = "INIT_0";
        INIT           : state_name = "INIT";
        CHECK_BIT      : state_name = "CHECK_BIT";
        SHIFT_BIT      : state_name = "SHIFT_BIT";
        ASSIGN_TEMP    : state_name = "ASSIGN_TEMP";
        CHECK_A        : state_name = "CHECK_A";
        ASSIGN_A       : state_name = "ASSIGN_A";
        SHIFT_RES_ADD  : state_name = "SHIFT_RES_ADD";
        ASSIGN_RES     : state_name = "ASSIGN_RES";
        SHIFT_RES_ONLY : state_name = "SHIFT_RES_ONLY";
        END_STATE      : state_name = "END_STATE";

        default:
            state_name = "UNKNOWN";

    endcase

end

`endif

endmodule

Raiz/raiz_verilog/comp.v
module comp (

    input [31:0] A,
    input [31:0] bit1,
    input [31:0] temp,

    output z,
    output bit_gt_a,
    output a_ge_temp

);

assign z = (bit1 == 0);
assign bit_gt_a   = (bit1 > A);
assign a_ge_temp  = (A >= temp);

endmodule

Raiz/raiz_verilog/alu.v
module alu (
    input [31:0] A,
    input [31:0] B,
    input alu_op,

    output reg [31:0] result
);

always @(*) begin

    case(alu_op)

        0:
            result = A + B;

        1:
            result = A - B;

    endcase

end
    
endmodule

Raiz/raiz_verilog/mux.v
module mux(

    input [31:0] A,
    input [31:0] B,
    input [31:0] C,
    input [31:0] D,

    input [1:0] sel,

    output reg [31:0] Y

);

always @(*) begin

    case(sel)

        2'b00:
            Y = A;

        2'b01:
            Y = B;

        2'b10:
            Y = C;
        
        // 2'b11:
        //     Y = D;

        default:
            Y = 32'd0;

    endcase

end

endmodule

Raiz/raiz_verilog/reg_Basic.v
module reg_Basic(
    input clk,
    input [31:0] in,
    input [31:0] alu_out,
    input load,
    input wr,

    output reg [31:0] out
);

always @(negedge clk) begin

    if(load)
        out <= in;

    else if(wr)
        out <= alu_out;

end

endmodule

Raiz/raiz_verilog/reg_Shift2.v
module reg_Shift2(
    input clk,

    input [31:0] alu_out,

    input shift,
    input load,
    input wr,

    output reg [31:0] bit1
);

always @(negedge clk) begin

    if(load)
        bit1 <= 32'h40000000;

    else if(wr)
        bit1 <= alu_out;

    else if(shift)
        bit1 <= bit1 >> 2;

end

endmodule

Raiz/raiz_verilog/reg_Shift1.v
module reg_Shift1(
    input clk,

    input [31:0] alu_out,

    input shift,
    input load,
    input wr,

    output reg [31:0] res
);

always @(negedge clk) begin

    if(load)
        res <= 0;

    else if(wr)
        res <= alu_out;

    else if(shift)
        res <= res >> 1;

end

endmodule

Raiz/raiz_verilog/raiz32.v
module raiz32 (
    input clk,
    input rst,
    input start,

    input [31:0] A,

    output [31:0] Result,
    output done

);

    wire load, wr_a, shift_res, wr_res, shift_bit, wr_bit, wr_temp, sel_op;
    wire [1:0] sel_A;
    wire [1:0] sel_B;
    wire z, bit_gt_a, a_ge_temp;
    wire [31:0] alu_out;

    wire [31:0] reg_A_out ;
    wire [31:0] reg_res_out ;
    wire [31:0] reg_bit_out ;
    wire [31:0] reg_temp_out ;

    wire [31:0] aluA_in ;
    wire [31:0] aluB_in ;


    reg_Basic reg_A(
        .clk(clk),
        .in(A),
        .alu_out(alu_out),
        .load(load),
        .wr(wr_a),
        .out(reg_A_out)
    );
    reg_Shift1 reg_res(
        .clk(clk),
        .alu_out(alu_out),
        .shift(shift_res),
        .load(load),
        .wr(wr_res),
        .res(reg_res_out)
    );
    reg_Shift2 reg_bit(
        .clk(clk),
        .alu_out(alu_out),
        .shift(shift_bit),
        .load(load),
        .wr(wr_bit),
        .bit1(reg_bit_out)
    );
    reg_Basic reg_temp(
        .clk(clk),
        .in(32'b0),
        .alu_out(alu_out),
        .load(load),
        .wr(wr_temp),
        .out(reg_temp_out)
    );

    mux muxA(
        .A(reg_bit_out),
        .B(reg_res_out),
        .C(reg_A_out),
        // .D(reg_res_out>>1),
        .sel(sel_A),
        .Y(aluA_in)
    );
    mux muxB(
        .A(reg_res_out),
        .B(reg_bit_out),
        .C(reg_temp_out),
        // .D(0),
        .sel(sel_B),
        .Y(aluB_in)
    );
    alu alu1(
        .A(aluA_in),
        .B(aluB_in),
        .alu_op(sel_op),
        .result(alu_out)
    );
    comp comp1(
        .A(reg_A_out),
        .bit1(reg_bit_out),
        .temp(reg_temp_out),
        .z(z),
        .bit_gt_a(bit_gt_a),
        .a_ge_temp(a_ge_temp)
    );
    control_raiz ctrl(
        .clk(clk),
        .start(start),
        .rst(rst),
        .z(z),
        .bit_gt_a(bit_gt_a),
        .a_ge_temp(a_ge_temp),
        .load(load),
        .wr_a(wr_a),
        .shift_res(shift_res),
        .wr_res(wr_res),
        .shift_bit(shift_bit),
        .wr_bit(wr_bit),
        .wr_temp(wr_temp),
        .sel_A(sel_A),
        .sel_B(sel_B),
        .sel_op(sel_op),
        .done(done)
    );
    assign Result = reg_res_out[31:0];
endmodule

Raiz/raiz_verilog/raiz32_TB.v
`timescale 1ns / 1ps

module raiz32_TB;

reg clk;
reg rst;
reg start;

reg [31:0] A;

wire [31:0] Result;
wire done;

raiz32 DUT(
    .clk(clk),
    .rst(rst),
    .start(start),
    .A(A),
    .Result(Result),
    .done(done)
);

parameter PERIOD = 20;

initial
    clk = 0;

always #(PERIOD/2)
    clk = ~clk;

task run_test;

    input [31:0] value;
    input [31:0] expected;

begin

    @(negedge clk);

    A = value;
    start = 1;

    @(negedge clk);

    start = 0;

    wait(done);

    @(negedge clk);

    if(Result == expected)
        $display("PASS | A = %d | Result = %d", value, Result);
    else
        $display("FAIL | A = %d | Result = %d | Expected = %d",
                 value, Result, expected);

    @(negedge clk);

end

endtask

initial begin

    rst = 0;
    start = 0;
    A = 0;

    @(negedge clk);
    rst = 1;

    @(negedge clk);
    rst = 0;

    run_test(0, 0);
    run_test(1, 1);
    run_test(4, 2);
    run_test(9, 3);
    run_test(16, 4);
    run_test(25, 5);
    run_test(36,6);
    //run_test(121, 11);
    run_test(1024, 32);
    //run_test(65535, 255);
   
   #100;

    $finish;

end

initial begin

    $dumpfile("raiz32_TB.vcd");
    $dumpvars(0, raiz32_TB);

end

endmodule

Raiz/raiz_verilog/raiz32_TB.vcd
$date
	Mon May 25 09:42:04 2026
$end
$version
	Icarus Verilog
$end
$timescale
	1ps
$end
$scope module raiz32_TB $end
$var wire 1 ! done $end
$var wire 32 " Result [31:0] $end
$var parameter 32 # PERIOD $end
$var reg 32 $ A [31:0] $end
$var reg 1 % clk $end
$var reg 1 & rst $end
$var reg 1 ' start $end
$scope module DUT $end
$var wire 32 ( A [31:0] $end
$var wire 32 ) Result [31:0] $end
$var wire 1 % clk $end
$var wire 1 & rst $end
$var wire 1 ' start $end
$var wire 1 * z $end
$var wire 1 + wr_temp $end
$var wire 1 , wr_res $end
$var wire 1 - wr_bit $end
$var wire 1 . wr_a $end
$var wire 1 / shift_res $end
$var wire 1 0 shift_bit $end
$var wire 1 1 sel_op $end
$var wire 2 2 sel_B [1:0] $end
$var wire 2 3 sel_A [1:0] $end
$var wire 32 4 reg_temp_out [31:0] $end
$var wire 32 5 reg_res_out [31:0] $end
$var wire 32 6 reg_bit_out [31:0] $end
$var wire 32 7 reg_A_out [31:0] $end
$var wire 1 8 load $end
$var wire 1 ! done $end
$var wire 1 9 bit_gt_a $end
$var wire 32 : alu_out [31:0] $end
$var wire 32 ; aluB_in [31:0] $end
$var wire 32 < aluA_in [31:0] $end
$var wire 1 = a_ge_temp $end
$scope module alu1 $end
$var wire 1 1 alu_op $end
$var wire 32 > B [31:0] $end
$var wire 32 ? A [31:0] $end
$var reg 32 @ result [31:0] $end
$upscope $end
$scope module comp1 $end
$var wire 1 * z $end
$var wire 32 A temp [31:0] $end
$var wire 1 9 bit_gt_a $end
$var wire 32 B bit1 [31:0] $end
$var wire 1 = a_ge_temp $end
$var wire 32 C A [31:0] $end
$upscope $end
$scope module ctrl $end
$var wire 1 = a_ge_temp $end
$var wire 1 9 bit_gt_a $end
$var wire 1 % clk $end
$var wire 1 & rst $end
$var wire 1 ' start $end
$var wire 1 * z $end
$var parameter 4 D ASSIGN_A $end
$var parameter 4 E ASSIGN_RES $end
$var parameter 4 F ASSIGN_TEMP $end
$var parameter 4 G CHECK_A $end
$var parameter 4 H CHECK_BIT $end
$var parameter 4 I END_STATE $end
$var parameter 4 J INIT $end
$var parameter 4 K INIT_0 $end
$var parameter 4 L SHIFT_BIT $end
$var parameter 4 M SHIFT_RES_ADD $end
$var parameter 4 N SHIFT_RES_ONLY $end
$var reg 1 ! done $end
$var reg 1 8 load $end
$var reg 2 O sel_A [1:0] $end
$var reg 2 P sel_B [1:0] $end
$var reg 1 1 sel_op $end
$var reg 1 0 shift_bit $end
$var reg 1 / shift_res $end
$var reg 4 Q state [3:0] $end
$var reg 320 R state_name [320:1] $end
$var reg 1 . wr_a $end
$var reg 1 - wr_bit $end
$var reg 1 , wr_res $end
$var reg 1 + wr_temp $end
$upscope $end
$scope module muxA $end
$var wire 32 S D [31:0] $end
$var wire 2 T sel [1:0] $end
$var wire 32 U C [31:0] $end
$var wire 32 V B [31:0] $end
$var wire 32 W A [31:0] $end
$var reg 32 X Y [31:0] $end
$upscope $end
$scope module muxB $end
$var wire 32 Y D [31:0] $end
$var wire 2 Z sel [1:0] $end
$var wire 32 [ C [31:0] $end
$var wire 32 \ B [31:0] $end
$var wire 32 ] A [31:0] $end
$var reg 32 ^ Y [31:0] $end
$upscope $end
$scope module reg_A $end
$var wire 32 _ alu_out [31:0] $end
$var wire 1 % clk $end
$var wire 32 ` in [31:0] $end
$var wire 1 8 load $end
$var wire 1 . wr $end
$var reg 32 a out [31:0] $end
$upscope $end
$scope module reg_bit $end
$var wire 32 b alu_out [31:0] $end
$var wire 1 % clk $end
$var wire 1 8 load $end
$var wire 1 0 shift $end
$var wire 1 - wr $end
$var reg 32 c bit1 [31:0] $end
$upscope $end
$scope module reg_res $end
$var wire 32 d alu_out [31:0] $end
$var wire 1 % clk $end
$var wire 1 8 load $end
$var wire 1 / shift $end
$var wire 1 , wr $end
$var reg 32 e res [31:0] $end
$upscope $end
$scope module reg_temp $end
$var wire 32 f alu_out [31:0] $end
$var wire 1 % clk $end
$var wire 32 g in [31:0] $end
$var wire 1 8 load $end
$var wire 1 + wr $end
$var reg 32 h out [31:0] $end
$upscope $end
$upscope $end
$scope task run_test $end
$var reg 32 i expected [31:0] $end
$var reg 32 j value [31:0] $end
$upscope $end
$upscope $end
$enddefinitions $end
$comment Show the parameter values. $end
$dumpall
b1000 N
b1010 M
b11 L
b0 K
b1 J
b1001 I
b10 H
b101 G
b100 F
b111 E
b110 D
b10100 #
$end
#0
$dumpvars
bx j
bx i
bx h
b0 g
bx f
bx e
bx d
bx c
bx b
bx a
b0 `
bx _
bx ^
bx ]
bx \
bx [
bx Z
bz Y
bx X
bx W
bx V
bx U
bx T
bz S
bx R
bx Q
bx P
bx O
bx C
bx B
bx A
bx @
bx ?
bx >
x=
bx <
bx ;
bx :
x9
x8
bx 7
bx 6
bx 5
bx 4
bx 3
bx 2
x1
x0
x/
x.
x-
x,
x+
x*
bx )
b0 (
0'
0&
0%
b0 $
bx "
x!
$end
#10000
b10010010100111001001001010101000101111100110000 R
0!
01
b0 2
b0 P
b0 Z
b0 3
b0 O
b0 T
0+
0-
00
0,
0/
0.
08
b0 Q
1%
#20000
1&
0%
#30000
1%
#40000
b0 i
b0 j
0&
0%
#50000
1%
#60000
1'
0%
#70000
18
b1001001010011100100100101010100 R
b1 Q
1%
#80000
b1000000000000000000000000000000 :
b1000000000000000000000000000000 @
b1000000000000000000000000000000 _
b1000000000000000000000000000000 b
b1000000000000000000000000000000 d
b1000000000000000000000000000000 f
b1000000000000000000000000000000 <
b1000000000000000000000000000000 ?
b1000000000000000000000000000000 X
b0 ;
b0 >
b0 ^
1=
19
b0 7
b0 C
b0 U
b0 a
b0 "
b0 )
b0 5
b0 V
b0 ]
b0 e
0*
b1000000000000000000000000000000 6
b1000000000000000000000000000000 B
b1000000000000000000000000000000 W
b1000000000000000000000000000000 \
b1000000000000000000000000000000 c
b0 4
b0 A
b0 [
b0 h
0'
0%
#90000
b10000110100100001000101010000110100101101011111010000100100100101010100 R
08
b10 Q
1%
#100000
0%
#110000
10
b10100110100100001001001010001100101010001011111010000100100100101010100 R
b11 Q
1%
#120000
b10000000000000000000000000000 :
b10000000000000000000000000000 @
b10000000000000000000000000000 _
b10000000000000000000000000000 b
b10000000000000000000000000000 d
b10000000000000000000000000000 f
b10000000000000000000000000000 <
b10000000000000000000000000000 ?
b10000000000000000000000000000 X
b10000000000000000000000000000 6
b10000000000000000000000000000 B
b10000000000000000000000000000 W
b10000000000000000000000000000 \
b10000000000000000000000000000 c
0%
#130000
b10000110100100001000101010000110100101101011111010000100100100101010100 R
00
b10 Q
1%
#140000
0%
#150000
10
b10100110100100001001001010001100101010001011111010000100100100101010100 R
b11 Q
1%
#160000
b100000000000000000000000000 :
b100000000000000000000000000 @
b100000000000000000000000000 _
b100000000000000000000000000 b
b100000000000000000000000000 d
b100000000000000000000000000 f
b100000000000000000000000000 <
b100000000000000000000000000 ?
b100000000000000000000000000 X
b100000000000000000000000000 6
b100000000000000000000000000 B
b100000000000000000000000000 W
b100000000000000000000000000 \
b100000000000000000000000000 c
0%
#170000
b10000110100100001000101010000110100101101011111010000100100100101010100 R
00
b10 Q
1%
#180000
0%
#190000
10
b10100110100100001001001010001100101010001011111010000100100100101010100 R
b11 Q
1%
#200000
b1000000000000000000000000 :
b1000000000000000000000000 @
b1000000000000000000000000 _
b1000000000000000000000000 b
b1000000000000000000000000 d
b1000000000000000000000000 f
b1000000000000000000000000 <
b1000000000000000000000000 ?
b1000000000000000000000000 X
b1000000000000000000000000 6
b1000000000000000000000000 B
b1000000000000000000000000 W
b1000000000000000000000000 \
b1000000000000000000000000 c
0%
#210000
b10000110100100001000101010000110100101101011111010000100100100101010100 R
00
b10 Q
1%
#220000
0%
#230000
10
b10100110100100001001001010001100101010001011111010000100100100101010100 R
b11 Q
1%
#240000
b10000000000000000000000 :
b10000000000000000000000 @
b10000000000000000000000 _
b10000000000000000000000 b
b10000000000000000000000 d
b10000000000000000000000 f
b10000000000000000000000 <
b10000000000000000000000 ?
b10000000000000000000000 X
b10000000000000000000000 6
b10000000000000000000000 B
b10000000000000000000000 W
b10000000000000000000000 \
b10000000000000000000000 c
0%
#250000
b10000110100100001000101010000110100101101011111010000100100100101010100 R
00
b10 Q
1%
#260000
0%
#270000
10
b10100110100100001001001010001100101010001011111010000100100100101010100 R
b11 Q
1%
#280000
b100000000000000000000 :
b100000000000000000000 @
b100000000000000000000 _
b100000000000000000000 b
b100000000000000000000 d
b100000000000000000000 f
b100000000000000000000 <
b100000000000000000000 ?
b100000000000000000000 X
b100000000000000000000 6
b100000000000000000000 B
b100000000000000000000 W
b100000000000000000000 \
b100000000000000000000 c
0%
#290000
b10000110100100001000101010000110100101101011111010000100100100101010100 R
00
b10 Q
1%
#300000
0%
#310000
10
b10100110100100001001001010001100101010001011111010000100100100101010100 R
b11 Q
1%
#320000
b1000000000000000000 :
b1000000000000000000 @
b1000000000000000000 _
b1000000000000000000 b
b1000000000000000000 d
b1000000000000000000 f
b1000000000000000000 <
b1000000000000000000 ?
b1000000000000000000 X
b1000000000000000000 6
b1000000000000000000 B
b1000000000000000000 W
b1000000000000000000 \
b1000000000000000000 c
0%
#330000
b10000110100100001000101010000110100101101011111010000100100100101010100 R
00
b10 Q
1%
#340000
0%
#350000
10
b10100110100100001001001010001100101010001011111010000100100100101010100 R
b11 Q
1%
#360000
b10000000000000000 :
b10000000000000000 @
b10000000000000000 _
b10000000000000000 b
b10000000000000000 d
b10000000000000000 f
b10000000000000000 <
b10000000000000000 ?
b10000000000000000 X
b10000000000000000 6
b10000000000000000 B
b10000000000000000 W
b10000000000000000 \
b10000000000000000 c
0%
#370000
b10000110100100001000101010000110100101101011111010000100100100101010100 R
00
b10 Q
1%
#380000
0%
#390000
10
b10100110100100001001001010001100101010001011111010000100100100101010100 R
b11 Q
1%
#400000
b100000000000000 :
b100000000000000 @
b100000000000000 _
b100000000000000 b
b100000000000000 d
b100000000000000 f
b100000000000000 <
b100000000000000 ?
b100000000000000 X
b100000000000000 6
b100000000000000 B
b100000000000000 W
b100000000000000 \
b100000000000000 c
0%
#410000
b10000110100100001000101010000110100101101011111010000100100100101010100 R
00
b10 Q
1%
#420000
0%
#430000
10
b10100110100100001001001010001100101010001011111010000100100100101010100 R
b11 Q
1%
#440000
b1000000000000 :
b1000000000000 @
b1000000000000 _
b1000000000000 b
b1000000000000 d
b1000000000000 f
b1000000000000 <
b1000000000000 ?
b1000000000000 X
b1000000000000 6
b1000000000000 B
b1000000000000 W
b1000000000000 \
b1000000000000 c
0%
#450000
b10000110100100001000101010000110100101101011111010000100100100101010100 R
00
b10 Q
1%
#460000
0%
#470000
10
b10100110100100001001001010001100101010001011111010000100100100101010100 R
b11 Q
1%
#480000
b10000000000 :
b10000000000 @
b10000000000 _
b10000000000 b
b10000000000 d
b10000000000 f
b10000000000 <
b10000000000 ?
b10000000000 X
b10000000000 6
b10000000000 B
b10000000000 W
b10000000000 \
b10000000000 c
0%
#490000
b10000110100100001000101010000110100101101011111010000100100100101010100 R
00
b10 Q
1%
#500000
0%
#510000
10
b10100110100100001001001010001100101010001011111010000100100100101010100 R
b11 Q
1%
#520000
b100000000 :
b100000000 @
b100000000 _
b100000000 b
b100000000 d
b100000000 f
b100000000 <
b100000000 ?
b100000000 X
b100000000 6
b100000000 B
b100000000 W
b100000000 \
b100000000 c
0%
#530000
b10000110100100001000101010000110100101101011111010000100100100101010100 R
00
b10 Q
1%
#540000
0%
#550000
10
b10100110100100001001001010001100101010001011111010000100100100101010100 R
b11 Q
1%
#560000
b1000000 :
b1000000 @
b1000000 _
b1000000 b
b1000000 d
b1000000 f
b1000000 <
b1000000 ?
b1000000 X
b1000000 6
b1000000 B
b1000000 W
b1000000 \
b1000000 c
0%
#570000
b10000110100100001000101010000110100101101011111010000100100100101010100 R
00
b10 Q
1%
#580000
0%
#590000
10
b10100110100100001001001010001100101010001011111010000100100100101010100 R
b11 Q
1%
#600000
b10000 :
b10000 @
b10000 _
b10000 b
b10000 d
b10000 f
b10000 <
b10000 ?
b10000 X
b10000 6
b10000 B
b10000 W
b10000 \
b10000 c
0%
#610000
b10000110100100001000101010000110100101101011111010000100100100101010100 R
00
b10 Q
1%
#620000
0%
#630000
10
b10100110100100001001001010001100101010001011111010000100100100101010100 R
b11 Q
1%
#640000
b100 :
b100 @
b100 _
b100 b
b100 d
b100 f
b100 <
b100 ?
b100 X
b100 6
b100 B
b100 W
b100 \
b100 c
0%
#650000
b10000110100100001000101010000110100101101011111010000100100100101010100 R
00
b10 Q
1%
#660000
0%
#670000
10
b10100110100100001001001010001100101010001011111010000100100100101010100 R
b11 Q
1%
#680000
b1 :
b1 @
b1 _
b1 b
b1 d
b1 f
b1 <
b1 ?
b1 X
b1 6
b1 B
b1 W
b1 \
b1 c
0%
#690000
b10000110100100001000101010000110100101101011111010000100100100101010100 R
00
b10 Q
1%
#700000
0%
#710000
10
b10100110100100001001001010001100101010001011111010000100100100101010100 R
b11 Q
1%
#720000
b0 :
b0 @
b0 _
b0 b
b0 d
b0 f
b0 <
b0 ?
b0 X
09
1*
b0 6
b0 B
b0 W
b0 \
b0 c
0%
#730000
b10001010100111001000100010111110101001101010100010000010101010001000101 R
1!
00
b1001 Q
1%
#740000
0%
#750000
0!
b10010010100111001001001010101000101111100110000 R
b0 Q
1%
#760000
b1 i
b1 j
0%
#770000
1%
#780000
1'
b1 $
b1 (
b1 `
0%
#790000
b1001001010011100100100101010100 R
18
b1 Q
1%
#800000
b1000000000000000000000000000000 :
b1000000000000000000000000000000 @
b1000000000000000000000000000000 _
b1000000000000000000000000000000 b
b1000000000000000000000000000000 d
b1000000000000000000000000000000 f
b1000000000000000000000000000000 <
b1000000000000000000000000000000 ?
b1000000000000000000000000000000 X
b1 7
b1 C
b1 U
b1 a
19
0*
b1000000000000000000000000000000 6
b1000000000000000000000000000000 B
b1000000000000000000000000000000 W
b1000000000000000000000000000000 \
b1000000000000000000000000000000 c
0'
0%
#810000
08
b10000110100100001000101010000110100101101011111010000100100100101010100 R
b10 Q
1%
#820000
0%
#830000
b10100110100100001001001010001100101010001011111010000100100100101010100 R
10
b11 Q
1%
#840000
b10000000000000000000000000000 :
b10000000000000000000000000000 @
b10000000000000000000000000000 _
b10000000000000000000000000000 b
b10000000000000000000000000000 d
b10000000000000000000000000000 f
b10000000000000000000000000000 <
b10000000000000000000000000000 ?
b10000000000000000000000000000 X
b10000000000000000000000000000 6
b10000000000000000000000000000 B
b10000000000000000000000000000 W
b10000000000000000000000000000 \
b10000000000000000000000000000 c
0%
#850000
00
b10000110100100001000101010000110100101101011111010000100100100101010100 R
b10 Q
1%
#860000
0%
#870000
b10100110100100001001001010001100101010001011111010000100100100101010100 R
10
b11 Q
1%
#880000
b100000000000000000000000000 :
b100000000000000000000000000 @
b100000000000000000000000000 _
b100000000000000000000000000 b
b100000000000000000000000000 d
b100000000000000000000000000 f
b100000000000000000000000000 <
b100000000000000000000000000 ?
b100000000000000000000000000 X
b100000000000000000000000000 6
b100000000000000000000000000 B
b100000000000000000000000000 W
b100000000000000000000000000 \
b100000000000000000000000000 c
0%
#890000
00
b10000110100100001000101010000110100101101011111010000100100100101010100 R
b10 Q
1%
#900000
0%
#910000
b10100110100100001001001010001100101010001011111010000100100100101010100 R
10
b11 Q
1%
#920000
b1000000000000000000000000 :
b1000000000000000000000000 @
b1000000000000000000000000 _
b1000000000000000000000000 b
b1000000000000000000000000 d
b1000000000000000000000000 f
b1000000000000000000000000 <
b1000000000000000000000000 ?
b1000000000000000000000000 X
b1000000000000000000000000 6
b1000000000000000000000000 B
b1000000000000000000000000 W
b1000000000000000000000000 \
b1000000000000000000000000 c
0%
#930000
00
b10000110100100001000101010000110100101101011111010000100100100101010100 R
b10 Q
1%
#940000
0%
#950000
b10100110100100001001001010001100101010001011111010000100100100101010100 R
10
b11 Q
1%
#960000
b10000000000000000000000 :
b10000000000000000000000 @
b10000000000000000000000 _
b10000000000000000000000 b
b10000000000000000000000 d
b10000000000000000000000 f
b10000000000000000000000 <
b10000000000000000000000 ?
b10000000000000000000000 X
b10000000000000000000000 6
b10000000000000000000000 B
b10000000000000000000000 W
b10000000000000000000000 \
b10000000000000000000000 c
0%
#970000
00
b10000110100100001000101010000110100101101011111010000100100100101010100 R
b10 Q
1%
#980000
0%
#990000
b10100110100100001001001010001100101010001011111010000100100100101010100 R
10
b11 Q
1%
#1000000
b100000000000000000000 :
b100000000000000000000 @
b100000000000000000000 _
b100000000000000000000 b
b100000000000000000000 d
b100000000000000000000 f
b100000000000000000000 <
b100000000000000000000 ?
b100000000000000000000 X
b100000000000000000000 6
b100000000000000000000 B
b100000000000000000000 W
b100000000000000000000 \
b100000000000000000000 c
0%
#1010000
00
b10000110100100001000101010000110100101101011111010000100100100101010100 R
b10 Q
1%
#1020000
0%
#1030000
b10100110100100001001001010001100101010001011111010000100100100101010100 R
10
b11 Q
1%
#1040000
b1000000000000000000 :
b1000000000000000000 @
b1000000000000000000 _
b1000000000000000000 b
b1000000000000000000 d
b1000000000000000000 f
b1000000000000000000 <
b1000000000000000000 ?
b1000000000000000000 X
b1000000000000000000 6
b1000000000000000000 B
b1000000000000000000 W
b1000000000000000000 \
b1000000000000000000 c
0%
#1050000
00
b10000110100100001000101010000110100101101011111010000100100100101010100 R
b10 Q
1%
#1060000
0%
#1070000
b10100110100100001001001010001100101010001011111010000100100100101010100 R
10
b11 Q
1%
#1080000
b10000000000000000 :
b10000000000000000 @
b10000000000000000 _
b10000000000000000 b
b10000000000000000 d
b10000000000000000 f
b10000000000000000 <
b10000000000000000 ?
b10000000000000000 X
b10000000000000000 6
b10000000000000000 B
b10000000000000000 W
b10000000000000000 \
b10000000000000000 c
0%
#1090000
00
b10000110100100001000101010000110100101101011111010000100100100101010100 R
b10 Q
1%
#1100000
0%
#1110000
b10100110100100001001001010001100101010001011111010000100100100101010100 R
10
b11 Q
1%
#1120000
b100000000000000 :
b100000000000000 @
b100000000000000 _
b100000000000000 b
b100000000000000 d
b100000000000000 f
b100000000000000 <
b100000000000000 ?
b100000000000000 X
b100000000000000 6
b100000000000000 B
b100000000000000 W
b100000000000000 \
b100000000000000 c
0%
#1130000
00
b10000110100100001000101010000110100101101011111010000100100100101010100 R
b10 Q
1%
#1140000
0%
#1150000
b10100110100100001001001010001100101010001011111010000100100100101010100 R
10
b11 Q
1%
#1160000
b1000000000000 :
b1000000000000 @
b1000000000000 _
b1000000000000 b
b1000000000000 d
b1000000000000 f
b1000000000000 <
b1000000000000 ?
b1000000000000 X
b1000000000000 6
b1000000000000 B
b1000000000000 W
b1000000000000 \
b1000000000000 c
0%
#1170000
00
b10000110100100001000101010000110100101101011111010000100100100101010100 R
b10 Q
1%
#1180000
0%
#1190000
b10100110100100001001001010001100101010001011111010000100100100101010100 R
10
b11 Q
1%
#1200000
b10000000000 :
b10000000000 @
b10000000000 _
b10000000000 b
b10000000000 d
b10000000000 f
b10000000000 <
b10000000000 ?
b10000000000 X
b10000000000 6
b10000000000 B
b10000000000 W
b10000000000 \
b10000000000 c
0%
#1210000
00
b10000110100100001000101010000110100101101011111010000100100100101010100 R
b10 Q
1%
#1220000
0%
#1230000
b10100110100100001001001010001100101010001011111010000100100100101010100 R
10
b11 Q
1%
#1240000
b100000000 :
b100000000 @
b100000000 _
b100000000 b
b100000000 d
b100000000 f
b100000000 <
b100000000 ?
b100000000 X
b100000000 6
b100000000 B
b100000000 W
b100000000 \
b100000000 c
0%
#1250000
00
b10000110100100001000101010000110100101101011111010000100100100101010100 R
b10 Q
1%
#1260000
0%
#1270000
b10100110100100001001001010001100101010001011111010000100100100101010100 R
10
b11 Q
1%
#1280000
b1000000 :
b1000000 @
b1000000 _
b1000000 b
b1000000 d
b1000000 f
b1000000 <
b1000000 ?
b1000000 X
b1000000 6
b1000000 B
b1000000 W
b1000000 \
b1000000 c
0%
#1290000
00
b10000110100100001000101010000110100101101011111010000100100100101010100 R
b10 Q
1%
#1300000
0%
#1310000
b10100110100100001001001010001100101010001011111010000100100100101010100 R
10
b11 Q
1%
#1320000
b10000 :
b10000 @
b10000 _
b10000 b
b10000 d
b10000 f
b10000 <
b10000 ?
b10000 X
b10000 6
b10000 B
b10000 W
b10000 \
b10000 c
0%
#1330000
00
b10000110100100001000101010000110100101101011111010000100100100101010100 R
b10 Q
1%
