Divisor/div_verilog/div_control.v
module div_control (

    input clk,
    input rst,
    input start,
    input MSB_A,
    input z,

    output reg reset,
    output reg shift,
    output reg dec,
    output reg lsb_DV,
    output reg r_A,
    output reg done

);

parameter INIT       = 3'b000,
          SHIFT_DV   = 3'b001,
          CHECK_MSB  = 3'b010,
          ASSIGN_DV  = 3'b011,
          CHECK_C    = 3'b100,
          DONE_STATE = 3'b101;

reg [2:0] state;

reg [5:0] count;

always @(posedge clk) begin

    if (rst) begin

        state <= INIT;
        count <= 0;

    end

    else begin

        case (state)

            //================================================
            // ESTADO INICIAL
            //================================================

            INIT: begin

                reset  <= 1;
                shift  <= 0;
                dec    <= 0;
                lsb_DV <= 0;
                r_A    <= 0;
                done   <= 0;

                count <= 0;

                if (start)
                    state <= SHIFT_DV;
                else
                    state <= INIT;

            end

            //================================================
            // DESPLAZAMIENTO Y DECREMENTO
            //================================================

            SHIFT_DV: begin

                reset  <= 0;
                shift  <= 1;
                dec    <= 1;
                lsb_DV <= 0;
                r_A    <= 0;
                done   <= 0;

                state <= CHECK_MSB;

            end

            //================================================
            // VERIFICAR SIGNO DE LA RESTA
            //================================================

            CHECK_MSB: begin

                reset  <= 0;
                shift  <= 0;
                dec    <= 0;
                lsb_DV <= 0;
                r_A    <= 0;
                done   <= 0;

                if (MSB_A == 0)
                    state <= ASSIGN_DV;
                else
                    state <= CHECK_C;

            end

            //================================================
            // ESCRIBIR BIT 1 EN EL COCIENTE
            // Y CARGAR NUEVO A
            //================================================

            ASSIGN_DV: begin

                reset  <= 0;
                shift  <= 0;
                dec    <= 0;
                lsb_DV <= 1;
                r_A    <= 1;
                done   <= 0;

                state <= CHECK_C;

            end

            //================================================
            // VERIFICAR CONTADOR
            //================================================

            CHECK_C: begin

                reset  <= 0;
                shift  <= 0;
                dec    <= 0;
                lsb_DV <= 0;
                r_A    <= 0;
                done   <= 0;

                if (z)
                    state <= DONE_STATE;
                else
                    state <= SHIFT_DV;

            end

            //================================================
            // FINALIZACIÓN
            //================================================

            DONE_STATE: begin

                reset  <= 0;
                shift  <= 0;
                dec    <= 0;
                lsb_DV <= 0;
                r_A    <= 0;
                done   <= 1;

                count <= count + 1;

                if (count > 28)
                    state <= INIT;
                else
                    state <= DONE_STATE;

            end

            //================================================
            // DEFAULT
            //================================================

            default: begin

                reset  <= 1;
                shift  <= 0;
                dec    <= 0;
                lsb_DV <= 0;
                r_A    <= 0;
                done   <= 0;

                state <= INIT;

            end

        endcase
    end
end

`ifdef BENCH

reg [8*40:1] state_name;

always @(*)
begin
    case(state)

        INIT  : state_name = "INIT";
        CHECK_MSB : state_name = "CHECK_DV";
        CHECK_C : state_name = "CHECK_C";
        ASSIGN_DV   : state_name = "ASSING_DV";
        SHIFT_DV : state_name = "SHIFT_DV";
        DONE_STATE   : state_name = "DONE_STATE";

        default:
            state_name = "UNKNOWN";

    endcase
end

`endif
endmodule

Divisor/div_verilog/check_c.v
module check_c (
    input [4:0] c,
    output z
);

 assign z = (c == 0);
endmodule

Divisor/div_verilog/contador.v
module contador (
    input clk,
    input reset,
    input dec,

    output reg [4:0] c
);


always @(negedge clk) begin

    if (reset) begin
        c <= 5'b10000;
    end

    else if (dec && c != 0) begin
        c <= c - 1'b1;
    end

end

endmodule

Divisor/div_verilog/resta.v
module resta (

    input  [15:0] A_in,
    input  [15:0] DR_in,

    output reg MSB_A,
    output reg [15:0] A

);

reg [15:0] temp;

always @(*) begin

    temp = A_in + (~DR_in) + 16'd1;

    A     = temp;
    MSB_A = temp[15];

end

endmodule

Divisor/div_verilog/left_shift_register.v
module left_shift_register(
    input clk,
    input reset,
    input shift,
    input r_A,
    input lsb_dv, //no se usa pero es practico tenerlo en cuenta para la ASM

    input [15:0] DV_in,
    input [15:0] A_in,

    output reg [15:0] A,
    output reg [15:0] r_out
);

reg [15:0] DV;

always @(negedge clk) begin
    if (reset) begin
        A     <= 0;
        DV    <= DV_in;
        r_out <= 0;
    end

    else if (shift) begin
        {A,DV} <= {A,DV} << 1;
        r_out <= DV;
    end

    else if (r_A) begin
        A     <= A_in;
        DV[0] <= 1'b1;
    end
end

endmodule

Divisor/div_verilog/divisor.v
module divisor (
    input clk,
    input rst,
    input start,

    input [15:0] A,
    input [15:0] B,

    output [15:0] Result,
    output done
); // reset = init
    wire reset, shift, dec, lsb_DV, r_A ;

    wire MSB_A;
    wire z;
    
    wire [4:0] c;
    wire [15:0] Result_resta;
    wire [15:0] Reg_A;

    left_shift_register left_shift (
        //señales de control
        .clk(clk),
        .reset(reset),
        .shift(shift),
        .r_A(r_A),
        .lsb_dv(lsb_DV), 
        //inputs
        .DV_in(A),
        .A_in(Result_resta),
        //outputs
        .A(Reg_A),
        .r_out(Result)
    );
    resta resta0(
        //inputs
        .A_in(Reg_A),
        .DR_in(B),
        //outputs
        .MSB_A(MSB_A),
        .A(Result_resta)
    );
    contador count(
        //INPUT
        .clk(clk),
        .reset(reset),
        .dec(dec),
        .c(c)
    );
    check_c check(
    //input
     .c(c),
    //output
     .z(z)
    );

    div_control ctrl(
        .clk(clk),
        .rst(rst),
        .start(start),
        .MSB_A(MSB_A),
        .z(z),

        .reset(reset),
        .shift(shift),
        .dec(dec),
        .lsb_DV(lsb_DV),
        .r_A(r_A),
        .done(done)
    );

endmodule

Divisor/div_verilog/divisor_TB.v
`timescale 1ns/1ps

module divisor_TB;

    reg clk;
    reg rst;
    reg start;

    reg [15:0] A;
    reg [15:0] B;

    wire [15:0] Result;
    wire done;

    //========================================================
    // INSTANCIA DEL DUT
    //========================================================

    divisor uut (
        .clk(clk),
        .rst(rst),
        .start(start),
        .A(A),
        .B(B),
        .Result(Result),
        .done(done)
    );

    //========================================================
    // GENERADOR DE CLOCK
    //========================================================

    initial begin
        clk = 0;
        forever #5 clk = ~clk;
    end

    //========================================================
    // ESTÍMULOS
    //========================================================

    initial begin

        // Inicialización
        rst   = 1;
        start = 0;
        A     = 0;
        B     = 0;

        #20;

        rst = 0;

        //====================================================
        // CASO 1
        // 25 / 5 = 5
        //====================================================

        @(negedge clk);
        A = 16'd25;
        B = 16'd5;

        @(negedge clk);
        start = 1;

        @(negedge clk);
        start = 0;

        wait(done);

        #20;

        $display("----------------------------------");
        $display("CASO 1");
        $display("A = %d", A);
        $display("B = %d", B);
        $display("Resultado = %d", Result);
        $display("----------------------------------");

        //====================================================
        // CASO 2
        // 100 / 4 = 25
        //====================================================

        rst = 1;
        #20;
        rst = 0;

        @(negedge clk);
        A = 16'd100;
        B = 16'd4;

        @(negedge clk);
        start = 1;

        @(negedge clk);
        start = 0;

        wait(done);

        #20;

        $display("----------------------------------");
        $display("CASO 2");
        $display("A = %d", A);
        $display("B = %d", B);
        $display("Resultado = %d", Result);
        $display("----------------------------------");

        //====================================================
        // CASO 3
        // 17 / 3 = 5
        //====================================================

        rst = 1;
        #20;
        rst = 0;

        @(negedge clk);
        A = 16'd17;
        B = 16'd3;

        @(negedge clk);
        start = 1;

        @(negedge clk);
        start = 0;

        wait(done);

        #20;

        $display("----------------------------------");
        $display("CASO 3");
        $display("A = %d", A);
        $display("B = %d", B);
        $display("Resultado = %d", Result);
        $display("----------------------------------");

        //====================================================
        // FINALIZAR SIMULACIÓN
        //====================================================

        #100;

        $finish;

    end

    initial begin

    $dumpfile("divisor_TB.vcd");
    $dumpvars(0, divisor_TB);

    end
endmodule

Divisor/div_verilog/divisor_TB.vcd
$date
	Wed May 13 16:07:16 2026
$end
$version
	Icarus Verilog
$end
$timescale
	1ps
$end
$scope module divisor_TB $end
$var wire 1 ! done $end
$var wire 16 " Result [15:0] $end
$var reg 16 # A [15:0] $end
$var reg 16 $ B [15:0] $end
$var reg 1 % clk $end
$var reg 1 & rst $end
$var reg 1 ' start $end
$scope module uut $end
$var wire 16 ( A [15:0] $end
$var wire 16 ) B [15:0] $end
$var wire 1 % clk $end
$var wire 1 & rst $end
$var wire 1 ' start $end
$var wire 1 * z $end
$var wire 1 + shift $end
$var wire 1 , reset $end
$var wire 1 - r_A $end
$var wire 1 . lsb_DV $end
$var wire 1 ! done $end
$var wire 1 / dec $end
$var wire 5 0 c [4:0] $end
$var wire 16 1 Result_resta [15:0] $end
$var wire 16 2 Result [15:0] $end
$var wire 16 3 Reg_A [15:0] $end
$var wire 1 4 MSB_A $end
$scope module check $end
$var wire 1 * z $end
$var wire 5 5 c [4:0] $end
$upscope $end
$scope module count $end
$var wire 1 % clk $end
$var wire 1 , reset $end
$var wire 1 / dec $end
$var reg 5 6 c [4:0] $end
$upscope $end
$scope module ctrl $end
$var wire 1 % clk $end
$var wire 1 & rst $end
$var wire 1 ' start $end
$var wire 1 * z $end
$var wire 1 4 MSB_A $end
$var parameter 3 7 ASSIGN_DV $end
$var parameter 3 8 CHECK_C $end
$var parameter 3 9 CHECK_MSB $end
$var parameter 3 : DONE_STATE $end
$var parameter 3 ; INIT $end
$var parameter 3 < SHIFT_DV $end
$var reg 6 = count [5:0] $end
$var reg 1 / dec $end
$var reg 1 ! done $end
$var reg 1 . lsb_DV $end
$var reg 1 - r_A $end
$var reg 1 , reset $end
$var reg 1 + shift $end
$var reg 3 > state [2:0] $end
$var reg 320 ? state_name [320:1] $end
$upscope $end
$scope module left_shift $end
$var wire 16 @ DV_in [15:0] $end
$var wire 1 % clk $end
$var wire 1 . lsb_dv $end
$var wire 1 - r_A $end
$var wire 1 , reset $end
$var wire 1 + shift $end
$var wire 16 A A_in [15:0] $end
$var reg 16 B A [15:0] $end
$var reg 16 C DV [15:0] $end
$var reg 16 D r_out [15:0] $end
$upscope $end
$scope module resta0 $end
$var wire 16 E A_in [15:0] $end
$var wire 16 F DR_in [15:0] $end
$var reg 16 G A [15:0] $end
$var reg 1 4 MSB_A $end
$var reg 16 H temp [15:0] $end
$upscope $end
$upscope $end
$upscope $end
$enddefinitions $end
$comment Show the parameter values. $end
$dumpall
b1 <
b0 ;
b101 :
b10 9
b100 8
b11 7
$end
#0
$dumpvars
bx H
bx G
b0 F
bx E
bx D
bx C
bx B
bx A
b0 @
bx ?
bx >
bx =
bx 6
bx 5
x4
bx 3
bx 2
bx 1
bx 0
x/
x.
x-
x,
x+
x*
b0 )
b0 (
0'
1&
0%
b0 $
b0 #
bx "
x!
$end
#5000
b1001001010011100100100101010100 ?
b0 =
b0 >
1%
#10000
0%
#15000
1%
#20000
b101 $
b101 )
b101 F
b11001 #
b11001 (
b11001 @
0%
0&
#25000
0!
0-
0.
0/
0+
1,
1%
#30000
14
b1111111111111011 1
b1111111111111011 A
b1111111111111011 G
b1111111111111011 H
0*
b10000 0
b10000 5
b10000 6
b0 "
b0 2
b0 D
b11001 C
b0 3
b0 B
b0 E
1'
0%
#35000
b101001101001000010010010100011001010100010111110100010001010110 ?
b1 >
1%
#40000
0'
0%
#45000
b100001101001000010001010100001101001011010111110100010001010110 ?
b10 >
1/
1+
0,
1%
#50000
b1111 0
b1111 5
b1111 6
b11001 "
b11001 2
b11001 D
b110010 C
0%
#55000
b1000011010010000100010101000011010010110101111101000011 ?
b100 >
0/
0+
1%
#60000
0%
#65000
b101001101001000010010010100011001010100010111110100010001010110 ?
b1 >
1%
#70000
0%
#75000
b100001101001000010001010100001101001011010111110100010001010110 ?
b10 >
1/
1+
1%
#80000
b110010 "
b110010 2
b110010 D
b1100100 C
b1110 0
b1110 5
b1110 6
0%
#85000
b1000011010010000100010101000011010010110101111101000011 ?
b100 >
0/
0+
1%
#90000
0%
#95000
b101001101001000010010010100011001010100010111110100010001010110 ?
b1 >
1%
#100000
0%
#105000
b100001101001000010001010100001101001011010111110100010001010110 ?
b10 >
1/
1+
1%
#110000
b1101 0
b1101 5
b1101 6
b1100100 "
b1100100 2
b1100100 D
b11001000 C
0%
#115000
b1000011010010000100010101000011010010110101111101000011 ?
b100 >
0/
0+
1%
#120000
0%
#125000
b101001101001000010010010100011001010100010111110100010001010110 ?
b1 >
1%
#130000
0%
#135000
b100001101001000010001010100001101001011010111110100010001010110 ?
b10 >
1/
1+
1%
#140000
b11001000 "
b11001000 2
b11001000 D
b110010000 C
b1100 0
b1100 5
b1100 6
0%
#145000
b1000011010010000100010101000011010010110101111101000011 ?
b100 >
0/
0+
1%
#150000
0%
#155000
b101001101001000010010010100011001010100010111110100010001010110 ?
b1 >
1%
#160000
0%
#165000
b100001101001000010001010100001101001011010111110100010001010110 ?
b10 >
1/
1+
1%
#170000
b1011 0
b1011 5
b1011 6
b110010000 "
b110010000 2
b110010000 D
b1100100000 C
0%
#175000
b1000011010010000100010101000011010010110101111101000011 ?
b100 >
0/
0+
1%
#180000
0%
#185000
b101001101001000010010010100011001010100010111110100010001010110 ?
b1 >
1%
#190000
0%
#195000
b100001101001000010001010100001101001011010111110100010001010110 ?
b10 >
1/
1+
1%
#200000
b1100100000 "
b1100100000 2
b1100100000 D
b11001000000 C
b1010 0
b1010 5
b1010 6
0%
#205000
b1000011010010000100010101000011010010110101111101000011 ?
b100 >
0/
0+
1%
#210000
0%
#215000
b101001101001000010010010100011001010100010111110100010001010110 ?
b1 >
1%
#220000
0%
#225000
b100001101001000010001010100001101001011010111110100010001010110 ?
b10 >
1/
1+
1%
#230000
b1001 0
b1001 5
b1001 6
b11001000000 "
b11001000000 2
b11001000000 D
b110010000000 C
0%
#235000
b1000011010010000100010101000011010010110101111101000011 ?
b100 >
0/
0+
1%
#240000
0%
#245000
b101001101001000010010010100011001010100010111110100010001010110 ?
b1 >
1%
#250000
0%
#255000
b100001101001000010001010100001101001011010111110100010001010110 ?
b10 >
1/
1+
1%
#260000
b110010000000 "
b110010000000 2
b110010000000 D
b1100100000000 C
b1000 0
b1000 5
b1000 6
0%
#265000
b1000011010010000100010101000011010010110101111101000011 ?
b100 >
0/
0+
1%
#270000
0%
#275000
b101001101001000010010010100011001010100010111110100010001010110 ?
b1 >
1%
#280000
0%
#285000
b100001101001000010001010100001101001011010111110100010001010110 ?
b10 >
1/
1+
1%
#290000
b111 0
b111 5
b111 6
b1100100000000 "
b1100100000000 2
b1100100000000 D
b11001000000000 C
0%
#295000
b1000011010010000100010101000011010010110101111101000011 ?
b100 >
0/
0+
1%
#300000
0%
#305000
b101001101001000010010010100011001010100010111110100010001010110 ?
b1 >
1%
#310000
0%
#315000
b100001101001000010001010100001101001011010111110100010001010110 ?
b10 >
1/
1+
1%
#320000
b11001000000000 "
b11001000000000 2
b11001000000000 D
b110010000000000 C
b110 0
b110 5
b110 6
0%
#325000
b1000011010010000100010101000011010010110101111101000011 ?
b100 >
0/
0+
1%
#330000
0%
#335000
b101001101001000010010010100011001010100010111110100010001010110 ?
b1 >
1%
#340000
0%
#345000
b100001101001000010001010100001101001011010111110100010001010110 ?
b10 >
1/
1+
1%
#350000
b101 0
b101 5
b101 6
b110010000000000 "
b110010000000000 2
b110010000000000 D
b1100100000000000 C
0%
#355000
b1000011010010000100010101000011010010110101111101000011 ?
b100 >
0/
0+
1%
#360000
0%
#365000
b101001101001000010010010100011001010100010111110100010001010110 ?
b1 >
1%
#370000
0%
#375000
b100001101001000010001010100001101001011010111110100010001010110 ?
b10 >
1/
1+
1%
#380000
b1111111111111100 1
b1111111111111100 A
b1111111111111100 G
b1111111111111100 H
b1100100000000000 "
b1100100000000000 2
b1100100000000000 D
b1 3
b1 B
b1 E
b1001000000000000 C
b100 0
b100 5
b100 6
0%
#385000
b1000011010010000100010101000011010010110101111101000011 ?
b100 >
0/
0+
1%
#390000
0%
#395000
b101001101001000010010010100011001010100010111110100010001010110 ?
b1 >
1%
#400000
0%
#405000
b100001101001000010001010100001101001011010111110100010001010110 ?
b10 >
1/
1+
1%
#410000
b1111111111111110 1
b1111111111111110 A
b1111111111111110 G
b1111111111111110 H
b11 0
b11 5
b11 6
b1001000000000000 "
b1001000000000000 2
b1001000000000000 D
b11 3
b11 B
b11 E
b10000000000000 C
0%
#415000
b1000011010010000100010101000011010010110101111101000011 ?
b100 >
0/
0+
1%
#420000
0%
#425000
b101001101001000010010010100011001010100010111110100010001010110 ?
b1 >
1%
#430000
0%
#435000
b100001101001000010001010100001101001011010111110100010001010110 ?
b10 >
1/
1+
1%
#440000
04
b1 1
b1 A
b1 G
b1 H
b10000000000000 "
b10000000000000 2
b10000000000000 D
b110 3
b110 B
b110 E
b100000000000000 C
b10 0
b10 5
b10 6
0%
#445000
b10000010101001101010011010010010100111001000111010111110100010001010110 ?
b11 >
0/
0+
1%
#450000
0%
#455000
b1000011010010000100010101000011010010110101111101000011 ?
b100 >
1-
1.
1%
#460000
14
b1111111111111100 1
b1111111111111100 A
b1111111111111100 G
b1111111111111100 H
b100000000000001 C
b1 3
b1 B
b1 E
0%
#465000
b101001101001000010010010100011001010100010111110100010001010110 ?
b1 >
0-
0.
1%
#470000
0%
#475000
b100001101001000010001010100001101001011010111110100010001010110 ?
b10 >
1/
1+
1%
#480000
b1111111111111101 1
b1111111111111101 A
b1111111111111101 G
b1111111111111101 H
b100000000000001 "
b100000000000001 2
b100000000000001 D
b10 3
b10 B
b10 E
b1000000000000010 C
b1 0
b1 5
b1 6
0%
#485000
b1000011010010000100010101000011010010110101111101000011 ?
b100 >
0/
0+
1%
#490000
0%
#495000
b101001101001000010010010100011001010100010111110100010001010110 ?
b1 >
1%
#500000
0%
#505000
b100001101001000010001010100001101001011010111110100010001010110 ?
b10 >
1/
1+
1%
#510000
04
b0 1
b0 A
b0 G
b0 H
1*
b0 0
b0 5
b0 6
b1000000000000010 "
b1000000000000010 2
b1000000000000010 D
b101 3
b101 B
b101 E
b100 C
0%
#515000
b10000010101001101010011010010010100111001000111010111110100010001010110 ?
b11 >
0/
0+
1%
#520000
0%
#525000
b1000011010010000100010101000011010010110101111101000011 ?
b100 >
1-
1.
1%
#530000
14
b1111111111111011 1
b1111111111111011 A
b1111111111111011 G
b1111111111111011 H
b101 C
b0 3
b0 B
b0 E
0%
#535000
b1000100010011110100111001000101010111110101001101010100010000010101010001000101 ?
b101 >
0-
0.
1%
#540000
0%
#545000
b1 =
1!
1%
#550000
0%
#555000
b10 =
1%
#560000
0%
#565000
b1001001010011100100100101010100 ?
b0 =
b0 >
1%
1&
#570000
0%
#575000
1%
#580000
0%
#585000
0!
1,
1%
0&
#590000
0*
b10000 0
b10000 5
b10000 6
b0 "
b0 2
b0 D
b1100100 C
b1111111111111100 1
b1111111111111100 A
b1111111111111100 G
b1111111111111100 H
b100 $
b100 )
b100 F
b1100100 #
b1100100 (
b1100100 @
0%
#595000
1%
#600000
1'
0%
#605000
b101001101001000010010010100011001010100010111110100010001010110 ?
b1 >
1%
#610000
0'
0%
#615000
b100001101001000010001010100001101001011010111110100010001010110 ?
b10 >
1/
1+
0,
1%
#620000
b1100100 "
b1100100 2
b1100100 D
b11001000 C
b1111 0
b1111 5
b1111 6
0%
#625000
b1000011010010000100010101000011010010110101111101000011 ?
b100 >
0/
0+
1%
#630000
0%
#635000
b101001101001000010010010100011001010100010111110100010001010110 ?
b1 >
1%
#640000
0%
#645000
b100001101001000010001010100001101001011010111110100010001010110 ?
b10 >
1/
1+
1%
#650000
b1110 0
b1110 5
b1110 6
b11001000 "
b11001000 2
b11001000 D
b110010000 C
0%
#655000
b1000011010010000100010101000011010010110101111101000011 ?
b100 >
0/
0+
1%
#660000
0%
#665000
b101001101001000010010010100011001010100010111110100010001010110 ?
b1 >
1%
#670000
0%
#675000
b100001101001000010001010100001101001011010111110100010001010110 ?
b10 >
1/
1+
1%
#680000
b110010000 "
b110010000 2
b110010000 D
b1100100000 C
b1101 0
b1101 5
b1101 6
0%
#685000
b1000011010010000100010101000011010010110101111101000011 ?
b100 >
0/
0+
1%
#690000
0%
#695000
b101001101001000010010010100011001010100010111110100010001010110 ?
b1 >
1%
#700000
0%
#705000
b100001101001000010001010100001101001011010111110100010001010110 ?
b10 >
1/
1+
1%
#710000
b1100 0
b1100 5
b1100 6
b1100100000 "
b1100100000 2
b1100100000 D
b11001000000 C
0%
#715000
b1000011010010000100010101000011010010110101111101000011 ?
b100 >
0/
0+
1%
#720000
0%
#725000
b101001101001000010010010100011001010100010111110100010001010110 ?
b1 >
1%
#730000
0%
#735000
b100001101001000010001010100001101001011010111110100010001010110 ?
b10 >
1/
1+
1%
#740000
b11001000000 "
b11001000000 2
b11001000000 D
b110010000000 C
b1011 0
b1011 5
b1011 6
0%
#745000
b1000011010010000100010101000011010010110101111101000011 ?
b100 >
0/
0+
1%
#750000
0%
#755000
b101001101001000010010010100011001010100010111110100010001010110 ?
b1 >
1%
#760000
0%
#765000
b100001101001000010001010100001101001011010111110100010001010110 ?
b10 >
1/
1+
1%
#770000
b1010 0
b1010 5
b1010 6
b110010000000 "
b110010000000 2
b110010000000 D
b1100100000000 C
0%
#775000
b1000011010010000100010101000011010010110101111101000011 ?
b100 >
0/
0+
1%
#780000
0%
#785000
b101001101001000010010010100011001010100010111110100010001010110 ?
b1 >
1%
#790000
0%
#795000
b100001101001000010001010100001101001011010111110100010001010110 ?
b10 >
1/
1+
1%
#800000
b1100100000000 "
b1100100000000 2
b1100100000000 D
b11001000000000 C
b1001 0
b1001 5
b1001 6
0%
#805000
b1000011010010000100010101000011010010110101111101000011 ?
b100 >
0/
0+
1%
#810000
0%
#815000
b101001101001000010010010100011001010100010111110100010001010110 ?
b1 >
1%
#820000
0%
#825000
b100001101001000010001010100001101001011010111110100010001010110 ?
b10 >
1/
1+
1%
#830000
b1000 0
b1000 5
b1000 6
b11001000000000 "
b11001000000000 2
b11001000000000 D
b110010000000000 C
0%
#835000
b1000011010010000100010101000011010010110101111101000011 ?
b100 >
0/
0+
1%
#840000
0%
#845000
b101001101001000010010010100011001010100010111110100010001010110 ?
b1 >
1%
#850000
0%
#855000
b100001101001000010001010100001101001011010111110100010001010110 ?
b10 >
1/
1+
1%
#860000
b110010000000000 "
b110010000000000 2
b110010000000000 D
b1100100000000000 C
b111 0
b111 5
b111 6
0%
#865000
b1000011010010000100010101000011010010110101111101000011 ?
b100 >
0/
0+
1%
#870000
0%
#875000
b101001101001000010010010100011001010100010111110100010001010110 ?
b1 >
1%
#880000
0%
#885000
b100001101001000010001010100001101001011010111110100010001010110 ?
b10 >
1/
1+
1%
#890000
b1111111111111101 1
b1111111111111101 A
b1111111111111101 G
b1111111111111101 H
b110 0
b110 5
b110 6
b1100100000000000 "
b1100100000000000 2
b1100100000000000 D
b1 3
b1 B
b1 E
b1001000000000000 C
0%
#895000
b1000011010010000100010101000011010010110101111101000011 ?
b100 >
0/
0+
1%
#900000
0%
#905000
b101001101001000010010010100011001010100010111110100010001010110 ?
b1 >
1%
#910000
0%
#915000
b100001101001000010001010100001101001011010111110100010001010110 ?
b10 >
1/
1+
1%
#920000
b1111111111111111 1
b1111111111111111 A
b1111111111111111 G
b1111111111111111 H
b1001000000000000 "
b1001000000000000 2
b1001000000000000 D
b11 3
b11 B
b11 E
b10000000000000 C
b101 0
b101 5
b101 6
0%
#925000
b1000011010010000100010101000011010010110101111101000011 ?
b100 >
0/
0+
1%
#930000
0%
#935000
b101001101001000010010010100011001010100010111110100010001010110 ?
b1 >
1%
#940000
0%
#945000
b100001101001000010001010100001101001011010111110100010001010110 ?
b10 >
1/
1+
1%
#950000
04
b10 1
b10 A
b10 G
b10 H
b100 0
b100 5
b100 6
b10000000000000 "
b10000000000000 2
b10000000000000 D
b110 3
b110 B
b110 E
b100000000000000 C
0%
#955000
b10000010101001101010011010010010100111001000111010111110100010001010110 ?
b11 >
0/
0+
1%
#960000
0%
#965000
b1000011010010000100010101000011010010110101111101000011 ?
b100 >
1-
1.
1%
#970000
14
b1111111111111110 1
b1111111111111110 A
b1111111111111110 G
b1111111111111110 H
b100000000000001 C
b10 3
b10 B
b10 E
0%
#975000
b101001101001000010010010100011001010100010111110100010001010110 ?
b1 >
0-
0.
1%
#980000
0%
#985000
b100001101001000010001010100001101001011010111110100010001010110 ?
b10 >
1/
1+
1%
#990000
04
b0 1
b0 A
b0 G
b0 H
b11 0
b11 5
b11 6
b100000000000001 "
b100000000000001 2
b100000000000001 D
b100 3
b100 B
b100 E
b1000000000000010 C
0%
#995000
b10000010101001101010011010010010100111001000111010111110100010001010110 ?
b11 >
0/
0+
1%
#1000000
0%
#1005000
b1000011010010000100010101000011010010110101111101000011 ?
b100 >
1-
1.
1%
#1010000
14
b1111111111111100 1
b1111111111111100 A
b1111111111111100 G
b1111111111111100 H
b1000000000000011 C
b0 3
b0 B
b0 E
0%
#1015000
b101001101001000010010010100011001010100010111110100010001010110 ?
b1 >
0-
0.
1%
#1020000
0%
#1025000
b100001101001000010001010100001101001011010111110100010001010110 ?
b10 >
1/
1+
1%
#1030000
b1111111111111101 1
b1111111111111101 A
b1111111111111101 G
b1111111111111101 H
b10 0
b10 5
b10 6
b1000000000000011 "
b1000000000000011 2
b1000000000000011 D
b1 3
b1 B
b1 E
b110 C
0%
#1035000
b1000011010010000100010101000011010010110101111101000011 ?
b100 >
0/
0+
1%
#1040000
0%
#1045000
b101001101001000010010010100011001010100010111110100010001010110 ?
b1 >
1%
#1050000
0%
#1055000
b100001101001000010001010100001101001011010111110100010001010110 ?
b10 >
1/
1+
1%
#1060000
b1111111111111110 1
b1111111111111110 A
b1111111111111110 G
b1111111111111110 H
b110 "
b110 2
b110 D
b10 3
b10 B
b10 E
b1100 C
b1 0
b1 5
b1 6
0%
#1065000
b1000011010010000100010101000011010010110101111101000011 ?
b100 >
0/
0+
1%
#1070000
0%
#1075000
b101001101001000010010010100011001010100010111110100010001010110 ?
b1 >
1%
#1080000
0%
#1085000
b100001101001000010001010100001101001011010111110100010001010110 ?
b10 >
1/
1+
1%
#1090000
04
b0 1
b0 A
b0 G
b0 H
1*
b0 0
b0 5
b0 6
b1100 "
b1100 2
b1100 D
b100 3
b100 B
b100 E
b11000 C
0%
#1095000
b10000010101001101010011010010010100111001000111010111110100010001010110 ?
b11 >
0/
0+
1%
#1100000
0%
#1105000
b1000011010010000100010101000011010010110101111101000011 ?
b100 >
1-
1.
1%
#1110000
14
b1111111111111100 1
b1111111111111100 A
b1111111111111100 G
b1111111111111100 H
b11001 C
b0 3
b0 B
b0 E
0%
#1115000
b1000100010011110100111001000101010111110101001101010100010000010101010001000101 ?
b101 >
0-
0.
1%
#1120000
0%
#1125000
b1 =
1!
1%
#1130000
0%
#1135000
b10 =
1%
#1140000
0%
#1145000
b1001001010011100100100101010100 ?
b0 =
b0 >
1%
1&
#1150000
0%
#1155000
1%
#1160000
0%
#1165000
0!
1,
1%
0&
#1170000
0*
b10000 0
b10000 5
b10000 6
b0 "
b0 2
b0 D
b10001 C
b1111111111111101 1
b1111111111111101 A
b1111111111111101 G
b1111111111111101 H
b11 $
b11 )
b11 F
b10001 #
b10001 (
b10001 @
0%
#1175000
1%
#1180000
1'
0%
#1185000
b101001101001000010010010100011001010100010111110100010001010110 ?
b1 >
1%
#1190000
0'
0%
#1195000
b100001101001000010001010100001101001011010111110100010001010110 ?
b10 >
1/
1+
0,
1%
#1200000
b10001 "
b10001 2
b10001 D
b100010 C
b1111 0
b1111 5
b1111 6
0%
#1205000
b1000011010010000100010101000011010010110101111101000011 ?
b100 >
0/
0+
1%
#1210000
0%
#1215000
b101001101001000010010010100011001010100010111110100010001010110 ?
b1 >
1%
#1220000
0%
#1225000
b100001101001000010001010100001101001011010111110100010001010110 ?
b10 >
1/
1+
1%
#1230000
b1110 0
b1110 5
b1110 6
b100010 "
b100010 2
b100010 D
b1000100 C
0%
#1235000
b1000011010010000100010101000011010010110101111101000011 ?
b100 >
0/
0+
1%
#1240000
0%
#1245000
b101001101001000010010010100011001010100010111110100010001010110 ?
b1 >
1%
#1250000
0%
#1255000
b100001101001000010001010100001101001011010111110100010001010110 ?
b10 >
1/
1+
1%
#1260000
b1000100 "
b1000100 2
b1000100 D
b10001000 C
b1101 0
b1101 5
b1101 6
0%
#1265000
b1000011010010000100010101000011010010110101111101000011 ?
b100 >
0/
0+
1%
#1270000
0%
#1275000
b101001101001000010010010100011001010100010111110100010001010110 ?
b1 >
1%
#1280000
0%
#1285000
b100001101001000010001010100001101001011010111110100010001010110 ?
b10 >
1/
1+
1%
#1290000
b1100 0
b1100 5
b1100 6
b10001000 "
b10001000 2
b10001000 D
b100010000 C
0%
#1295000
b1000011010010000100010101000011010010110101111101000011 ?
b100 >
0/
0+
1%
#1300000
0%
#1305000
b101001101001000010010010100011001010100010111110100010001010110 ?
b1 >
1%
#1310000
0%
#1315000
b100001101001000010001010100001101001011010111110100010001010110 ?
b10 >
1/
1+
1%
#1320000
b100010000 "
b100010000 2
b100010000 D
b1000100000 C
b1011 0
b1011 5
b1011 6
0%
#1325000
b1000011010010000100010101000011010010110101111101000011 ?
b100 >
0/
0+
1%
#1330000
0%
#1335000
b101001101001000010010010100011001010100010111110100010001010110 ?
b1 >
1%
#1340000
0%
#1345000
b100001101001000010001010100001101001011010111110100010001010110 ?
b10 >
1/
1+
1%
#1350000
b1010 0
b1010 5
b1010 6
b1000100000 "
b1000100000 2
b1000100000 D
b10001000000 C
0%
#1355000
b1000011010010000100010101000011010010110101111101000011 ?
b100 >
0/
0+
1%
#1360000
0%
#1365000
b101001101001000010010010100011001010100010111110100010001010110 ?
b1 >
1%
#1370000
0%
#1375000
b100001101001000010001010100001101001011010111110100010001010110 ?
b10 >
1/
1+
1%
#1380000
b10001000000 "
b10001000000 2
b10001000000 D
b100010000000 C
b1001 0
b1001 5
b1001 6
0%
#1385000
b1000011010010000100010101000011010010110101111101000011 ?
b100 >
0/
0+
1%
#1390000
0%
#1395000
b101001101001000010010010100011001010100010111110100010001010110 ?
b1 >
1%
#1400000
0%
#1405000
b100001101001000010001010100001101001011010111110100010001010110 ?
b10 >
1/
1+
1%
